.gitignore
README.rst
setup.py
version.txt
csscheck/HISTORY.txt
csscheck/__init__.py
csscheck/commands.py
csscheck/main.py
csscheck/tests.py
csscheck/utils.py
csscheck.egg-info/PKG-INFO
csscheck.egg-info/SOURCES.txt
csscheck.egg-info/dependency_links.txt
csscheck.egg-info/entry_points.txt
csscheck.egg-info/requires.txt
csscheck.egg-info/top_level.txt
csscheck.egg-info/zip-safe
csscheck/samples/file1.css
csscheck/samples/file2.css
csscheck/samples/file3.css.dtml
csscheck/samples/ignored.py
csscheck/samples/subdir/file3.css
csscheck/samples/subdir/ignored.js