Metadata-Version: 1.0
Name: csscheck
Version: 1.0
Summary: Simple command line tool to help CSS developers
Home-page: UNKNOWN
Author: Vincent Pretre (Zest software)
Author-email: UNKNOWN
License: GPL
Platform: UNKNOWN
